README
setup.py
betcore/__init__.py
betcore/browser.py
betcore/exception.py
betcore/util.py
betcore/horse/AA.py
betcore/horse/AA_Admin.py
betcore/horse/DB.py
betcore/horse/DB_Admin.py
betcore/horse/LW.py
betcore/horse/LW_Admin.py
betcore/horse/__init__.py
betcore/horse/config.py
betcore/horse/mask.js
betcore/horse/text4.js
hsbcore.egg-info/PKG-INFO
hsbcore.egg-info/SOURCES.txt
hsbcore.egg-info/dependency_links.txt
hsbcore.egg-info/top_level.txt