Metadata-Version: 1.0
Name: hsbcore
Version: 1.0.0
Summary: for pv use
Home-page: http://www.baidu.com/asdf
Author: sky
Author-email: 2322222@qqw.com
License: MIT License
Keywords: hsbcore,pv
Platform: any
